reflex_chessboard/__init__.py
reflex_chessboard/chessboard.py
reflex_chessboard/py.typed
reflex_chessboard/pieces/cburnett/bB.svg
reflex_chessboard/pieces/cburnett/bK.svg
reflex_chessboard/pieces/cburnett/bN.svg
reflex_chessboard/pieces/cburnett/bP.svg
reflex_chessboard/pieces/cburnett/bQ.svg
reflex_chessboard/pieces/cburnett/bR.svg
reflex_chessboard/pieces/cburnett/wB.svg
reflex_chessboard/pieces/cburnett/wK.svg
reflex_chessboard/pieces/cburnett/wN.svg
reflex_chessboard/pieces/cburnett/wP.svg
reflex_chessboard/pieces/cburnett/wQ.svg
reflex_chessboard/pieces/cburnett/wR.svg
reflex_chessboard/pieces/maestro/bB.svg
reflex_chessboard/pieces/maestro/bK.svg
reflex_chessboard/pieces/maestro/bN.svg
reflex_chessboard/pieces/maestro/bP.svg
reflex_chessboard/pieces/maestro/bQ.svg
reflex_chessboard/pieces/maestro/bR.svg
reflex_chessboard/pieces/maestro/wB.svg
reflex_chessboard/pieces/maestro/wK.svg
reflex_chessboard/pieces/maestro/wN.svg
reflex_chessboard/pieces/maestro/wP.svg
reflex_chessboard/pieces/maestro/wQ.svg
reflex_chessboard/pieces/maestro/wR.svg
reflex_chessboard/pieces/merida/bB.svg
reflex_chessboard/pieces/merida/bK.svg
reflex_chessboard/pieces/merida/bN.svg
reflex_chessboard/pieces/merida/bP.svg
reflex_chessboard/pieces/merida/bQ.svg
reflex_chessboard/pieces/merida/bR.svg
reflex_chessboard/pieces/merida/wB.svg
reflex_chessboard/pieces/merida/wK.svg
reflex_chessboard/pieces/merida/wN.svg
reflex_chessboard/pieces/merida/wP.svg
reflex_chessboard/pieces/merida/wQ.svg
reflex_chessboard/pieces/merida/wR.svg
reflex_chessboard/pieces/pirouetti/bB.svg
reflex_chessboard/pieces/pirouetti/bK.svg
reflex_chessboard/pieces/pirouetti/bN.svg
reflex_chessboard/pieces/pirouetti/bP.svg
reflex_chessboard/pieces/pirouetti/bQ.svg
reflex_chessboard/pieces/pirouetti/bR.svg
reflex_chessboard/pieces/pirouetti/wB.svg
reflex_chessboard/pieces/pirouetti/wK.svg
reflex_chessboard/pieces/pirouetti/wN.svg
reflex_chessboard/pieces/pirouetti/wP.svg
reflex_chessboard/pieces/pirouetti/wQ.svg
reflex_chessboard-0.1.4.dist-info/licenses/LICENSE
reflex_chessboard-0.1.4.dist-info/METADATA
reflex_chessboard-0.1.4.dist-info/WHEEL
reflex_chessboard-0.1.4.dist-info/top_level.txt
reflex_chessboard-0.1.4.dist-info/RECORD
