Metadata-Version: 2.4
Name: reflex-chessboard
Version: 0.1.4
Summary: Шахматная доска для Reflex (react-chessboard + chess.js)
Author: kuruhuru
License-Expression: MIT
Project-URL: Homepage, https://github.com/kuruhuru/reflex-chessboard
Project-URL: Repository, https://github.com/kuruhuru/reflex-chessboard
Project-URL: Issues, https://github.com/kuruhuru/reflex-chessboard/issues
Keywords: reflex,reflex-custom-components
Classifier: Development Status :: 3 - Alpha
Classifier: Programming Language :: Python :: 3
Classifier: Programming Language :: Python :: 3 :: Only
Classifier: Programming Language :: Python :: 3.10
Classifier: Programming Language :: Python :: 3.11
Classifier: Programming Language :: Python :: 3.12
Requires-Python: >=3.10
License-File: LICENSE
Requires-Dist: reflex>=0.8.23
Provides-Extra: dev
Requires-Dist: build; extra == "dev"
Requires-Dist: twine; extra == "dev"
Requires-Dist: pytest; extra == "dev"
Requires-Dist: ruff; extra == "dev"
Dynamic: license-file
